Metadata-Version: 2.1
Name: build4s
Version: 1.0.4
Summary: A build tools for CodeBuild
Home-page: https://github.com/meanstrong/build4s
Author: pengmingqiang
Author-email: rockypengchina@outlook.com
Maintainer: pengmingqiang
Maintainer-email: rockypengchina@outlook.com
License: Apache 2.0
Platform: any
